{
  "slug": "monome",
  "name": "monome",
  "version": "1.0.0-pre",
  "license": "GPL-2.0",
  "author": "",
  "authorEmail": "",
  "authorUrl": "",
  "pluginUrl": "",
  "manualUrl": "https://monome.org/docs/modular/",
  "sourceUrl": "https://github.com/Dewb/monome-rack",
  "donateUrl": "",
  "modules": [
    {
      "slug": "whitewhale",
      "name": "whitewhale",
      "description": "grid-enabled probabilistic step sequencer",
      "tags": [
        "sequencer",
        "clock",
        "external"
      ]
    },
    {
      "slug": "earthsea",
      "name": "earthsea",
      "description": "grid-enabled shape-memory pattern instrument",
      "tags": [
        "sequencer",
        "external"
      ]
    },
    {
      "slug": "meadowphysics",
      "name": "meadowphysics",
      "description": "grid-enabled rhizomatic cascading counter",
      "tags": [
        "sequencer",
        "clock",
        "external"
      ]
    },
    {
      "slug": "grid128",
      "name": "grid128",
      "description": "",
      "tags": [
        "controller"
      ]
    },
    {
      "slug": "grid64",
      "name": "grid64",
      "description": "",
      "tags": [
        "controller"
      ]
    },
    {
      "slug": "grid128series",
      "name": "grid128series",
      "description": "",
      "tags": [
        "controller"
      ]
    },
    {
      "slug": "grid64series",
      "name": "grid64series",
      "description": "",
      "tags": [
        "controller"
      ]
    }
  ]
}